csgoinvshuffle/__init__.py
csgoinvshuffle/enums/__init__.py
csgoinvshuffle/enums/filters_enums.py
csgoinvshuffle/enums/item_types.py
csgoinvshuffle/enums/loadout_slots.py
csgoinvshuffle/enums/rarities.py
csgoinvshuffle/enums/teams.py
csgoinvshuffle/exceptions.py
csgoinvshuffle/inventory.py
csgoinvshuffle/item.py
csgoinvshuffle/shuffle.py
csgoinvshuffle/shuffleformat.py
csgoinvshuffle/types.py
csgoinvshuffle/utils.py
csgoinvshuffle-1.3.10.dist-info/METADATA
csgoinvshuffle-1.3.10.dist-info/LICENSE
csgoinvshuffle-1.3.10.dist-info/WHEEL
csgoinvshuffle-1.3.10.dist-info/RECORD
