Metadata-Version: 2.1
Name: csgoinvshuffle
Version: 1.3.10
Summary: A package for creating CS:GO inventory shuffle config files
Home-page: https://csgoinvshuffle.kreyoo.dev
License: MIT
Author: Jan Vollmer
Author-email: jan@vllmr.dev
Requires-Python: >=3.7,<4.0
Classifier: Development Status :: 5 - Production/Stable
Classifier: Intended Audience :: End Users/Desktop
Classifier: License :: OSI Approved :: MIT License
Classifier: Natural Language :: English
Classifier: Operating System :: OS Independent
Classifier: Programming Language :: Python :: 3
Classifier: Programming Language :: Python :: 3.7
Classifier: Programming Language :: Python :: 3.8
Classifier: Programming Language :: Python :: 3.9
Classifier: Programming Language :: Python :: 3.10
Classifier: Programming Language :: Python :: 3.11
Classifier: Topic :: Games/Entertainment :: First Person Shooters
Classifier: Topic :: Software Development :: Libraries :: Python Modules
Classifier: Typing :: Typed
Requires-Dist: Deprecated (>=1.2.13,<2.0.0)
Requires-Dist: requests (>=2.26.0,<3.0.0)
Requires-Dist: typing-extensions (>=4.0.1,<5.0.0)
Project-URL: Repository, https://github.com/jvllmr/csgo-inv-shuffle
